Metadata-Version: 1.0
Name: pybugger2
Version: 1.0
Summary: Pybugger is an easy to use color-supported CLI debugging tool for python.
Home-page: https://github.com/fareskalaboud/pybugger2
Author: fareskalaboud
Author-email: fares.alaboud@gmail.com
License: GNU General Public License v3.0
Platform: UNKNOWN
